README.md
setup.py
zip_dir.egg-info/PKG-INFO
zip_dir.egg-info/SOURCES.txt
zip_dir.egg-info/dependency_links.txt
zip_dir.egg-info/not-zip-safe
zip_dir.egg-info/requires.txt
zip_dir.egg-info/top_level.txt
zipdir/__init__.py